biographs/__init__.py
biographs/classes/__init__.py
biographs/classes/pmolecule.py
biographs/lib/__init__.py
biographs/lib/bgraph.py
biographs/lib/bpdb.py
biographs-0.1.dist-info/LICENSE
biographs-0.1.dist-info/METADATA
biographs-0.1.dist-info/WHEEL
biographs-0.1.dist-info/top_level.txt
biographs-0.1.dist-info/RECORD
